py_data_digger/__init__.py
py_data_digger/main.py
py_data_digger-0.2.0.dist-info/LICENSE
py_data_digger-0.2.0.dist-info/METADATA
py_data_digger-0.2.0.dist-info/WHEEL
py_data_digger-0.2.0.dist-info/RECORD
