Metadata-Version: 2.1
Name: py-data-digger
Version: 0.2.0
Summary: Safely navigate through unsafe data: dicts, tuples, lists, strings and objects
License: MIT
Author: Ramon G. Dias
Author-email: ramon.giovane@gmail.com
Requires-Python: >=3.9,<4.0
Classifier: License :: OSI Approved :: MIT License
Classifier: Programming Language :: Python :: 3
Classifier: Programming Language :: Python :: 3.9
Classifier: Programming Language :: Python :: 3.10
Classifier: Programming Language :: Python :: 3.11
Classifier: Programming Language :: Python :: 3.12
